ct_auth0_streamlit_component/__init__.py
ct_auth0_streamlit_component/frontend/build/asset-manifest.json
ct_auth0_streamlit_component/frontend/build/bootstrap.min.css
ct_auth0_streamlit_component/frontend/build/index.html
ct_auth0_streamlit_component/frontend/build/precache-manifest.ca76273fbc33015c413278d8c10891c2.js
ct_auth0_streamlit_component/frontend/build/service-worker.js
ct_auth0_streamlit_component/frontend/build/static/css/main.befd254f.chunk.css
ct_auth0_streamlit_component/frontend/build/static/css/main.befd254f.chunk.css.map
ct_auth0_streamlit_component/frontend/build/static/js/2.86677cf2.chunk.js
ct_auth0_streamlit_component/frontend/build/static/js/2.86677cf2.chunk.js.LICENSE.txt
ct_auth0_streamlit_component/frontend/build/static/js/2.86677cf2.chunk.js.map
ct_auth0_streamlit_component/frontend/build/static/js/main.18796dea.chunk.js
ct_auth0_streamlit_component/frontend/build/static/js/main.18796dea.chunk.js.map
ct_auth0_streamlit_component/frontend/build/static/js/runtime-main.11ec9aca.js
ct_auth0_streamlit_component/frontend/build/static/js/runtime-main.11ec9aca.js.map
ct_auth0_streamlit_component-0.0.3.dist-info/LICENSE
ct_auth0_streamlit_component-0.0.3.dist-info/METADATA
ct_auth0_streamlit_component-0.0.3.dist-info/WHEEL
ct_auth0_streamlit_component-0.0.3.dist-info/top_level.txt
ct_auth0_streamlit_component-0.0.3.dist-info/RECORD
